caasm_adapter_base/__init__.py
caasm_adapter_base/base.py
caasm_adapter_base/fetcher/__init__.py
caasm_adapter_base/fetcher/fetch_handler_base.py
caasm_adapter_base/fetcher/fetch_service_base.py
caasm_adapter_base/fetcher/cleaners/__init__.py
caasm_adapter_base/fetcher/cleaners/base.py
caasm_adapter_base/sdk/__init__.py
caasm_adapter_base/sdk/adapter_fetch.py
caasm_adapter_base/sdk/base.py
caasm_adapter_base/util/__init__.py
caasm_adapter_base/util/adapter_connection.py
caasm_adapter_base/util/adapter_fabric.py
caasm_adapter_base/util/adapter_fetch.py
caasm_adapter_base/util/client.py
caasm_adapter_base/util/constants.py
caasm_adapter_base/util/exception.py
caasm_adapter_base/util/connection_method/__init__.py
caasm_adapter_base/util/connection_method/base.py
caasm_adapter_base/util/connection_method/http.py
caasm_adapter_base/util/connection_method/mongodb.py
caasm_adapter_base/util/connection_method/mysql.py
caasm_config_base/__init__.py
caasm_config_base/config.py
caasm_config_base/default.yml
caasm_persistence_base/__init__.py
caasm_persistence_base/entity/__init__.py
caasm_persistence_base/entity/base.py
caasm_persistence_base/handler/__init__.py
caasm_persistence_base/handler/storage/__init__.py
caasm_persistence_base/handler/storage/_common.py
caasm_persistence_base/handler/storage/base.py
caasm_persistence_base/handler/storage/manager.py
caasm_persistence_base/handler/storage/model/__init__.py
caasm_persistence_base/handler/storage/model/response.py
caasm_persistence_base/schema/__init__.py
caasm_persistence_base/schema/base.py
caasm_service_base/__init__.py
caasm_service_base/constants/__init__.py
caasm_service_base/constants/adapter.py
caasm_service_base/constants/connection_method.py
caasm_service_base/entity/__init__.py
caasm_service_base/entity/adapter.py
caasm_service_base/schema/__init__.py
caasm_service_base/schema/adapter.py
caasm_service_base/schema/runtime.py
caasm_tool/__init__.py
caasm_tool/cache.py
caasm_tool/config.py
caasm_tool/constants.py
caasm_base-0.1.21.1.dist-info/METADATA
caasm_base-0.1.21.1.dist-info/WHEEL
caasm_base-0.1.21.1.dist-info/top_level.txt
caasm_base-0.1.21.1.dist-info/RECORD
