Metadata-Version: 2.1
Name: caasm-base
Version: 0.1.21.1
Summary: 未岚科技CAASM平台基础类库
Author: rendajiang@weilansec
Author-email: rendajiang@weilansec.com
Requires-Python: >=3.8
Requires-Dist: requests >=2.31.0
Requires-Dist: loguru ~=0.6.0
Requires-Dist: IPy ==1.1
Requires-Dist: dictlib ==1.1.5
Requires-Dist: PyYAML ==6.0.2
Requires-Dist: PySocks ==1.7.1
Requires-Dist: case-convert ==1.1.0
Requires-Dist: pymongo ==3.12.3
Requires-Dist: selenium ==4.24.0
Requires-Dist: selenium-wire ==5.1.0
Requires-Dist: PyMySQL ~=1.0.2
Requires-Dist: nanoid ==2.0.0
Requires-Dist: marshmallow ==3.14.1
Requires-Dist: marshmallow-enum ==1.5.1
Requires-Dist: blinker ==1.7.0
Requires-Dist: sqlparse ~=0.5.0
Requires-Dist: xlrd ==1.2.0
